data_provider/__init__.py
data_provider/__init__.pyi
data_provider/__pycache__/__init__.cpython-311.pyc
data_provider/__pycache__/_types.cpython-311.pyc
data_provider/_types.py
data_provider/data_provider.abi3.so
data_provider/data_provider.pyi
data_provider/py.typed
nextpoly_data_provider-0.10.1.dist-info/METADATA
nextpoly_data_provider-0.10.1.dist-info/WHEEL
nextpoly_data_provider-0.10.1.dist-info/RECORD
