Metadata-Version: 2.4
Name: nextpoly-data-provider
Version: 0.10.1
Classifier: Development Status :: 4 - Beta
Classifier: Intended Audience :: Developers
Classifier: License :: OSI Approved :: MIT License
Classifier: Programming Language :: Python :: 3
Classifier: Programming Language :: Python :: 3.11
Classifier: Programming Language :: Python :: 3.12
Classifier: Programming Language :: Python :: 3.13
Classifier: Programming Language :: Rust
Classifier: Topic :: Database
Summary: Data provider for Python - Query data from local DuckDB
Keywords: duckdb,prediction-market
Author: cupnfish
License: MIT
Requires-Python: >=3.11
Project-URL: Homepage, https://github.com/Unipredict/data-layer
Project-URL: Repository, https://github.com/Unipredict/data-layer
